humilis_elasticache
