Metadata-Version: 1.1
Name: humilis-elasticache
Version: 0.0.4
Summary: Humilis plug-in to deploy a Elasticache cluster
Home-page: https://github.com/humilis/humilis-elasticache
Author: German Gomez-Herrero, FindHotel BV
Author-email: german@findhotel.net
License: MIT
Platform: UNKNOWN
Classifier: Programming Language :: Python :: 3
